qiboconnection/__init__.py
qiboconnection/about.py
qiboconnection/api.py
qiboconnection/api_utils.py
qiboconnection/config.py
qiboconnection/connection.py
qiboconnection/errors.py
qiboconnection/util.py
qiboconnection/constants/__init__.py
qiboconnection/constants/constants.py
qiboconnection/models/__init__.py
qiboconnection/models/algorithm.py
qiboconnection/models/calibration.py
qiboconnection/models/job.py
qiboconnection/models/job_listing.py
qiboconnection/models/job_listing_item.py
qiboconnection/models/job_result.py
qiboconnection/models/runcard.py
qiboconnection/models/user.py
qiboconnection/models/devices/__init__.py
qiboconnection/models/devices/device.py
qiboconnection/models/devices/device_details.py
qiboconnection/models/devices/devices.py
qiboconnection/models/devices/util.py
qiboconnection/typings/__init__.py
qiboconnection/typings/auth_config.py
qiboconnection/typings/connection.py
qiboconnection/typings/job_data.py
qiboconnection/typings/vqa.py
qiboconnection/typings/devices/__init__.py
qiboconnection/typings/devices/device_input.py
qiboconnection/typings/enums/__init__.py
qiboconnection/typings/enums/algorithm_name.py
qiboconnection/typings/enums/algorythm_type.py
qiboconnection/typings/enums/device_status.py
qiboconnection/typings/enums/device_type.py
qiboconnection/typings/enums/grant_type.py
qiboconnection/typings/enums/initial_value.py
qiboconnection/typings/enums/job_status.py
qiboconnection/typings/enums/job_type.py
qiboconnection/typings/enums/str_enum.py
qiboconnection/typings/enums/token_type.py
qiboconnection/typings/enums/user_role.py
qiboconnection/typings/enums/user_scope.py
qiboconnection/typings/requests/__init__.py
qiboconnection/typings/requests/assertion_payload.py
qiboconnection/typings/requests/calibration_request.py
qiboconnection/typings/requests/job_request.py
qiboconnection/typings/requests/runcard_request.py
qiboconnection/typings/responses/__init__.py
qiboconnection/typings/responses/access_token_response.py
qiboconnection-0.23.2.dist-info/LICENSE
qiboconnection-0.23.2.dist-info/METADATA
qiboconnection-0.23.2.dist-info/WHEEL
qiboconnection-0.23.2.dist-info/top_level.txt
qiboconnection-0.23.2.dist-info/RECORD
