Metadata-Version: 2.1
Name: qiboconnection
Version: 0.23.2
Summary: Python interface to Qilimanjaro's Services for quantum job executions.
Home-page: https://github.com/qilimanjaro-tech/qiboconnection
Author: Qilimanjaro
Author-email: info@qilimanjaro.tech
Classifier: Programming Language :: Python :: 3
Classifier: Topic :: Scientific/Engineering :: Physics
Requires-Python: >=3.10.0
License-File: LICENSE
Requires-Dist: requests==2.32.3
Requires-Dist: typeguard==4.3.0
Requires-Dist: numpy==1.26.4
Requires-Dist: qibo==0.2.8
Requires-Dist: PyJWT==2.9.0
Requires-Dist: pandas~=1.5.3
Requires-Dist: websockets~=13.1
Provides-Extra: docs
Requires-Dist: sphinx; extra == "docs"
Requires-Dist: sphinx_rtd_theme; extra == "docs"
Requires-Dist: recommonmark; extra == "docs"
Requires-Dist: sphinxcontrib-bibtex; extra == "docs"
Requires-Dist: sphinx_markdown_tables; extra == "docs"
Requires-Dist: nbsphinx; extra == "docs"
Requires-Dist: IPython; extra == "docs"
Provides-Extra: tests
Requires-Dist: pytest; extra == "tests"
